Metadata-Version: 2.1
Name: cognitohashcalculator
Version: 1.0.0
Summary: A small python library for calculating the secret hash required for the amazon cognito's user and password authentication
Author: Om Khulbe
Author-email: omkhulbe53@gmail.com
Classifier: Programming Language :: Python :: 3
Classifier: License :: OSI Approved :: MIT License
Classifier: Operating System :: OS Independent
Requires-Python: >=3.6
